<?xml version="1.0" encoding="ASCII"?>
<henshin:Module xmi:version="2.0" xmlns:xmi="http://www.omg.org/XMI" xmlns:xsi="http://www.w3.org/2001/XMLSchema-instance" xmlns:henshin="http://www.eclipse.org/emf/2011/Henshin" xmi:id="_6NhrkJhdEeuLROdPHS5eqw">
  <units xsi:type="henshin:Rule" xmi:id="_6NhrkZhdEeuLROdPHS5eqw" name="rule" description="null, createPreserveNodeWithOutgoingEdge, addNAC, createPreserveNodeWithIncomingEdge">
    <lhs xmi:id="_6NhrkphdEeuLROdPHS5eqw" name="Lhs">
      <nodes xmi:id="_6Nhrk5hdEeuLROdPHS5eqw" incoming="_6NhrlphdEeuLROdPHS5eqw">
        <type href="http://nrp.model/nrp#//Requirement"/>
      </nodes>
      <nodes xmi:id="_6NhrlJhdEeuLROdPHS5eqw" outgoing="_6NhrlphdEeuLROdPHS5eqw _6Nhrl5hdEeuLROdPHS5eqw">
        <type href="http://nrp.model/nrp#//RequirementRealisation"/>
      </nodes>
      <nodes xmi:id="_6NhrlZhdEeuLROdPHS5eqw" incoming="_6Nhrl5hdEeuLROdPHS5eqw">
        <type href="http://nrp.model/nrp#//SoftwareArtifact"/>
      </nodes>
      <edges xmi:id="_6NhrlphdEeuLROdPHS5eqw" source="_6NhrlJhdEeuLROdPHS5eqw" target="_6Nhrk5hdEeuLROdPHS5eqw">
        <type href="http://nrp.model/nrp#//RequirementRealisation/requirement"/>
      </edges>
      <edges xmi:id="_6Nhrl5hdEeuLROdPHS5eqw" source="_6NhrlJhdEeuLROdPHS5eqw" target="_6NhrlZhdEeuLROdPHS5eqw">
        <type href="http://nrp.model/nrp#//RequirementRealisation/dependsOn"/>
      </edges>
      <formula xsi:type="henshin:Not" xmi:id="_6NhrmJhdEeuLROdPHS5eqw">
        <child xsi:type="henshin:NestedCondition" xmi:id="_6NhrmZhdEeuLROdPHS5eqw">
          <conclusion xmi:id="_6NhrmphdEeuLROdPHS5eqw">
            <nodes xmi:id="_6Nhrm5hdEeuLROdPHS5eqw" incoming="_6NhrnZhdEeuLROdPHS5eqw">
              <type href="http://nrp.model/nrp#//SoftwareArtifact"/>
            </nodes>
            <nodes xmi:id="_6NhrnJhdEeuLROdPHS5eqw" outgoing="_6NhrnZhdEeuLROdPHS5eqw">
              <type href="http://nrp.model/nrp#//RequirementRealisation"/>
            </nodes>
            <edges xmi:id="_6NhrnZhdEeuLROdPHS5eqw" source="_6NhrnJhdEeuLROdPHS5eqw" target="_6Nhrm5hdEeuLROdPHS5eqw">
              <type href="http://nrp.model/nrp#//RequirementRealisation/dependsOn"/>
            </edges>
          </conclusion>
          <mappings xmi:id="_6NhrnphdEeuLROdPHS5eqw" origin="_6NhrlJhdEeuLROdPHS5eqw" image="_6NhrnJhdEeuLROdPHS5eqw"/>
        </child>
      </formula>
    </lhs>
    <rhs xmi:id="_6Nhrn5hdEeuLROdPHS5eqw" name="Rhs">
      <nodes xmi:id="_6NhroJhdEeuLROdPHS5eqw" incoming="_6Nhro5hdEeuLROdPHS5eqw">
        <type href="http://nrp.model/nrp#//Requirement"/>
      </nodes>
      <nodes xmi:id="_6NhroZhdEeuLROdPHS5eqw" outgoing="_6Nhro5hdEeuLROdPHS5eqw _6NhrpJhdEeuLROdPHS5eqw">
        <type href="http://nrp.model/nrp#//RequirementRealisation"/>
      </nodes>
      <nodes xmi:id="_6NhrophdEeuLROdPHS5eqw" incoming="_6NhrpJhdEeuLROdPHS5eqw">
        <type href="http://nrp.model/nrp#//SoftwareArtifact"/>
      </nodes>
      <edges xmi:id="_6Nhro5hdEeuLROdPHS5eqw" source="_6NhroZhdEeuLROdPHS5eqw" target="_6NhroJhdEeuLROdPHS5eqw">
        <type href="http://nrp.model/nrp#//RequirementRealisation/requirement"/>
      </edges>
      <edges xmi:id="_6NhrpJhdEeuLROdPHS5eqw" source="_6NhroZhdEeuLROdPHS5eqw" target="_6NhrophdEeuLROdPHS5eqw">
        <type href="http://nrp.model/nrp#//RequirementRealisation/dependsOn"/>
      </edges>
    </rhs>
    <mappings xmi:id="_6NhrpZhdEeuLROdPHS5eqw" origin="_6Nhrk5hdEeuLROdPHS5eqw" image="_6NhroJhdEeuLROdPHS5eqw"/>
    <mappings xmi:id="_6NhrpphdEeuLROdPHS5eqw" origin="_6NhrlJhdEeuLROdPHS5eqw" image="_6NhroZhdEeuLROdPHS5eqw"/>
    <mappings xmi:id="_6Nhrp5hdEeuLROdPHS5eqw" origin="_6NhrlZhdEeuLROdPHS5eqw" image="_6NhrophdEeuLROdPHS5eqw"/>
  </units>
  <units xsi:type="henshin:Rule" xmi:id="_6NhrqJhdEeuLROdPHS5eqw" name="rule">
    <lhs xmi:id="_6NhrqZhdEeuLROdPHS5eqw" name="Lhs">
      <nodes xmi:id="_6NhrqphdEeuLROdPHS5eqw">
        <type href="http://nrp.model/nrp#//Cost"/>
      </nodes>
    </lhs>
    <rhs xmi:id="_6Nhrq5hdEeuLROdPHS5eqw" name="Rhs">
      <nodes xmi:id="_6NhrrJhdEeuLROdPHS5eqw">
        <type href="http://nrp.model/nrp#//Cost"/>
      </nodes>
    </rhs>
    <mappings xmi:id="_6NhrrZhdEeuLROdPHS5eqw" origin="_6NhrqphdEeuLROdPHS5eqw" image="_6NhrrJhdEeuLROdPHS5eqw"/>
  </units>
  <units xsi:type="henshin:Rule" xmi:id="_6NhrrphdEeuLROdPHS5eqw" name="rule" description="null, createPreserveEdgesWithNode, createPreserveNodeWithIncomingEdge, createCrOrDelEdge, createPreserveEdgesWithNode, createPreserveNodeWithIncomingEdge">
    <lhs xmi:id="_6Nhrr5hdEeuLROdPHS5eqw" name="Lhs">
      <nodes xmi:id="_6NhrsJhdEeuLROdPHS5eqw" incoming="_6Nhrt5hdEeuLROdPHS5eqw" outgoing="_6NhrtZhdEeuLROdPHS5eqw _6NhrtphdEeuLROdPHS5eqw _6NhruJhdEeuLROdPHS5eqw">
        <type href="http://nrp.model/nrp#//Solution"/>
      </nodes>
      <nodes xmi:id="_6NhrsZhdEeuLROdPHS5eqw" incoming="_6NhrtZhdEeuLROdPHS5eqw">
        <type href="http://nrp.model/nrp#//SoftwareArtifact"/>
      </nodes>
      <nodes xmi:id="_6NhrsphdEeuLROdPHS5eqw" incoming="_6NhrtphdEeuLROdPHS5eqw" outgoing="_6Nhrt5hdEeuLROdPHS5eqw">
        <type href="http://nrp.model/nrp#//SoftwareArtifact"/>
      </nodes>
      <nodes xmi:id="_6Nhrs5hdEeuLROdPHS5eqw" incoming="_6NhruJhdEeuLROdPHS5eqw" outgoing="_6NhruZhdEeuLROdPHS5eqw">
        <type href="http://nrp.model/nrp#//SoftwareArtifact"/>
      </nodes>
      <nodes xmi:id="_6NhrtJhdEeuLROdPHS5eqw" incoming="_6NhruZhdEeuLROdPHS5eqw">
        <type href="http://nrp.model/nrp#//RequirementRealisation"/>
      </nodes>
      <edges xmi:id="_6NhrtZhdEeuLROdPHS5eqw" source="_6NhrsJhdEeuLROdPHS5eqw" target="_6NhrsZhdEeuLROdPHS5eqw">
        <type href="http://nrp.model/nrp#//Solution/selectedArtifacts"/>
      </edges>
      <edges xmi:id="_6NhrtphdEeuLROdPHS5eqw" source="_6NhrsJhdEeuLROdPHS5eqw" target="_6NhrsphdEeuLROdPHS5eqw">
        <type href="http://nrp.model/nrp#//Solution/selectedArtifacts"/>
      </edges>
      <edges xmi:id="_6Nhrt5hdEeuLROdPHS5eqw" source="_6NhrsphdEeuLROdPHS5eqw" target="_6NhrsJhdEeuLROdPHS5eqw">
        <type href="http://nrp.model/nrp#//SoftwareArtifact/solutions"/>
      </edges>
      <edges xmi:id="_6NhruJhdEeuLROdPHS5eqw" source="_6NhrsJhdEeuLROdPHS5eqw" target="_6Nhrs5hdEeuLROdPHS5eqw">
        <type href="http://nrp.model/nrp#//Solution/selectedArtifacts"/>
      </edges>
      <edges xmi:id="_6NhruZhdEeuLROdPHS5eqw" source="_6Nhrs5hdEeuLROdPHS5eqw" target="_6NhrtJhdEeuLROdPHS5eqw">
        <type href="http://nrp.model/nrp#//SoftwareArtifact/contributesTo"/>
      </edges>
    </lhs>
    <rhs xmi:id="_6NhruphdEeuLROdPHS5eqw" name="Rhs">
      <nodes xmi:id="_6Nhru5hdEeuLROdPHS5eqw" outgoing="_6NhrwJhdEeuLROdPHS5eqw _6NhrwZhdEeuLROdPHS5eqw _6NhrwphdEeuLROdPHS5eqw">
        <type href="http://nrp.model/nrp#//Solution"/>
      </nodes>
      <nodes xmi:id="_6NhrvJhdEeuLROdPHS5eqw" incoming="_6NhrwJhdEeuLROdPHS5eqw">
        <type href="http://nrp.model/nrp#//SoftwareArtifact"/>
      </nodes>
      <nodes xmi:id="_6NhrvZhdEeuLROdPHS5eqw" incoming="_6NhrwZhdEeuLROdPHS5eqw">
        <type href="http://nrp.model/nrp#//SoftwareArtifact"/>
      </nodes>
      <nodes xmi:id="_6NhrvphdEeuLROdPHS5eqw" incoming="_6NhrwphdEeuLROdPHS5eqw" outgoing="_6Nhrw5hdEeuLROdPHS5eqw">
        <type href="http://nrp.model/nrp#//SoftwareArtifact"/>
      </nodes>
      <nodes xmi:id="_6Nhrv5hdEeuLROdPHS5eqw" incoming="_6Nhrw5hdEeuLROdPHS5eqw">
        <type href="http://nrp.model/nrp#//RequirementRealisation"/>
      </nodes>
      <edges xmi:id="_6NhrwJhdEeuLROdPHS5eqw" source="_6Nhru5hdEeuLROdPHS5eqw" target="_6NhrvJhdEeuLROdPHS5eqw">
        <type href="http://nrp.model/nrp#//Solution/selectedArtifacts"/>
      </edges>
      <edges xmi:id="_6NhrwZhdEeuLROdPHS5eqw" source="_6Nhru5hdEeuLROdPHS5eqw" target="_6NhrvZhdEeuLROdPHS5eqw">
        <type href="http://nrp.model/nrp#//Solution/selectedArtifacts"/>
      </edges>
      <edges xmi:id="_6NhrwphdEeuLROdPHS5eqw" source="_6Nhru5hdEeuLROdPHS5eqw" target="_6NhrvphdEeuLROdPHS5eqw">
        <type href="http://nrp.model/nrp#//Solution/selectedArtifacts"/>
      </edges>
      <edges xmi:id="_6Nhrw5hdEeuLROdPHS5eqw" source="_6NhrvphdEeuLROdPHS5eqw" target="_6Nhrv5hdEeuLROdPHS5eqw">
        <type href="http://nrp.model/nrp#//SoftwareArtifact/contributesTo"/>
      </edges>
    </rhs>
    <mappings xmi:id="_6NhrxJhdEeuLROdPHS5eqw" origin="_6NhrsJhdEeuLROdPHS5eqw" image="_6Nhru5hdEeuLROdPHS5eqw"/>
    <mappings xmi:id="_6NhrxZhdEeuLROdPHS5eqw" origin="_6NhrsZhdEeuLROdPHS5eqw" image="_6NhrvJhdEeuLROdPHS5eqw"/>
    <mappings xmi:id="_6NhrxphdEeuLROdPHS5eqw" origin="_6NhrsphdEeuLROdPHS5eqw" image="_6NhrvZhdEeuLROdPHS5eqw"/>
    <mappings xmi:id="_6Nhrx5hdEeuLROdPHS5eqw" origin="_6Nhrs5hdEeuLROdPHS5eqw" image="_6NhrvphdEeuLROdPHS5eqw"/>
    <mappings xmi:id="_6NhryJhdEeuLROdPHS5eqw" origin="_6NhrtJhdEeuLROdPHS5eqw" image="_6Nhrv5hdEeuLROdPHS5eqw"/>
  </units>
  <units xsi:type="henshin:Rule" xmi:id="_6NhryZhdEeuLROdPHS5eqw" name="rule" description="null, CreateMultiRuleWithMappedPreserveNode">
    <lhs xmi:id="_6NhryphdEeuLROdPHS5eqw" name="Lhs">
      <nodes xmi:id="_6Nhry5hdEeuLROdPHS5eqw">
        <type href="http://nrp.model/nrp#//Cost"/>
      </nodes>
    </lhs>
    <rhs xmi:id="_6NhrzJhdEeuLROdPHS5eqw" name="Rhs">
      <nodes xmi:id="_6NhrzZhdEeuLROdPHS5eqw">
        <type href="http://nrp.model/nrp#//Cost"/>
      </nodes>
    </rhs>
    <mappings xmi:id="_6NhrzphdEeuLROdPHS5eqw" origin="_6Nhry5hdEeuLROdPHS5eqw" image="_6NhrzZhdEeuLROdPHS5eqw"/>
    <multiRules xmi:id="_6Nhrz5hdEeuLROdPHS5eqw">
      <lhs xmi:id="_6Nhr0JhdEeuLROdPHS5eqw">
        <nodes xmi:id="_6Nhr0ZhdEeuLROdPHS5eqw">
          <type href="http://nrp.model/nrp#//Cost"/>
        </nodes>
      </lhs>
      <rhs xmi:id="_6Nhr0phdEeuLROdPHS5eqw">
        <nodes xmi:id="_6Nhr05hdEeuLROdPHS5eqw">
          <type href="http://nrp.model/nrp#//Cost"/>
        </nodes>
      </rhs>
      <mappings xmi:id="_6Nhr1JhdEeuLROdPHS5eqw" origin="_6Nhr0ZhdEeuLROdPHS5eqw" image="_6Nhr05hdEeuLROdPHS5eqw"/>
      <multiMappings xmi:id="_6Nhr1ZhdEeuLROdPHS5eqw" origin="_6Nhry5hdEeuLROdPHS5eqw" image="_6Nhr0ZhdEeuLROdPHS5eqw"/>
      <multiMappings xmi:id="_6Nhr1phdEeuLROdPHS5eqw" origin="_6NhrzZhdEeuLROdPHS5eqw" image="_6Nhr05hdEeuLROdPHS5eqw"/>
    </multiRules>
  </units>
</henshin:Module>
